{
  "$schema": "https://github.com/erdesigns-eu/Delphi-OBD/schema/dtc-catalog-v1.json",
  "version": 1,
  "name": "McLaren DTC starter",
  "default_source": "mclaren-mds-community",
  "dtcs": [
    { "code": "P0301", "severity": "warning",  "description": "McLaren M840T 4.0 V8 — Cylinder 1 misfire detected", "verified": false },
    { "code": "P0302", "severity": "warning",  "description": "McLaren V8 — Cylinder 2 misfire detected", "verified": false },
    { "code": "P0303", "severity": "warning",  "description": "McLaren V8 — Cylinder 3 misfire detected", "verified": false },
    { "code": "P0304", "severity": "warning",  "description": "McLaren V8 — Cylinder 4 misfire detected", "verified": false },
    { "code": "P0305", "severity": "warning",  "description": "McLaren V8 — Cylinder 5 misfire detected", "verified": false },
    { "code": "P0306", "severity": "warning",  "description": "McLaren V8 — Cylinder 6 misfire detected", "verified": false },
    { "code": "P0307", "severity": "warning",  "description": "McLaren V8 — Cylinder 7 misfire detected", "verified": false },
    { "code": "P0308", "severity": "warning",  "description": "McLaren V8 — Cylinder 8 misfire detected", "verified": false },
    { "code": "P0234", "severity": "critical", "description": "McLaren V8 twin-turbo — Turbocharger overboost", "verified": false },
    { "code": "P0299", "severity": "warning",  "description": "McLaren V8 — Turbocharger underboost", "verified": false },
    { "code": "P0524", "severity": "critical", "description": "McLaren — Engine oil pressure too low (dry-sump)", "verified": false },
    { "code": "P052E", "severity": "warning",  "description": "McLaren V8 — Camshaft phasing performance", "verified": false },
    { "code": "P0420", "severity": "warning",  "description": "McLaren — Catalyst Bank 1 efficiency below threshold", "verified": false },
    { "code": "P0430", "severity": "warning",  "description": "McLaren — Catalyst Bank 2 efficiency below threshold", "verified": false },
    { "code": "P0AA6", "severity": "critical", "description": "McLaren Artura — HV battery isolation fault", "verified": false },
    { "code": "P0A7A", "severity": "warning",  "description": "McLaren Artura — Hybrid battery pack deterioration", "verified": false },
    { "code": "P0D29", "severity": "warning",  "description": "McLaren Artura — AC charging coupler latch fault", "verified": false },
    { "code": "P2769", "severity": "warning",  "description": "McLaren — 7-DCT (SSG) torque-converter clutch performance", "verified": false },
    { "code": "C0050", "severity": "warning",  "description": "McLaren — Vehicle-Lift system pressure sensor", "verified": false },
    { "code": "C0090", "severity": "warning",  "description": "McLaren — Active rear-wing position sensor circuit", "verified": false },
    { "code": "U0073", "severity": "critical", "description": "McLaren — High-speed CAN bus 'A' off", "verified": false },
    { "code": "U0146", "severity": "warning",  "description": "McLaren — Lost Communication With Gateway 'A'", "verified": false },
    { "code": "U0184", "severity": "warning",  "description": "McLaren — Lost Communication With IRIS infotainment", "verified": false },
    { "code": "U0316", "severity": "warning",  "description": "McLaren — Lost Communication With PCCM (Proactive Chassis Control)", "verified": false }
  ]
}
